LICENSE
MANIFEST.in
README.rst
pyproject.toml
setup.cfg
setup.py
authentication/__init__.py
authentication/admin.py
authentication/apps.py
authentication/models.py
authentication/serializers.py
authentication/urls.py
authentication/views.py
djangorestframework_authentication.egg-info/PKG-INFO
djangorestframework_authentication.egg-info/SOURCES.txt
djangorestframework_authentication.egg-info/dependency_links.txt
djangorestframework_authentication.egg-info/requires.txt
djangorestframework_authentication.egg-info/top_level.txt